{
  "problems": [
    {
      "id": 1,
      "title": "Two Sum",
      "difficulty": "Easy",
      "category": "Hash Map",
      "num": 1,
      "path": "https://leetcode.com/problems/two-sum"
    },
    {
      "id": 2,
      "title": "Add Two Numbers",
      "difficulty": "Medium",
      "category": "Linked List",
      "num": 2,
      "path": "https://leetcode.com/problems/add-two-numbers"
    },
    {
      "id": 3,
      "title": "Longest Substring No Repeat",
      "difficulty": "Medium",
      "category": "Sliding Window",
      "num": 3,
      "path": "https://leetcode.com/problems/longest-substring-no-repeat"
    },
    {
      "id": 4,
      "title": "Longest Substring Without Repeating",
      "difficulty": "Medium",
      "category": "Sliding Window",
      "num": 3,
      "path": "https://leetcode.com/problems/longest-substring-no-repeat"
    },
    {
      "id": 5,
      "title": "Longest Substring Without Repeating Characters",
      "difficulty": "Medium",
      "category": "Sliding Window",
      "num": 3,
      "path": "https://leetcode.com/problems/longest-substring-no-repeat"
    },
    {
      "id": 6,
      "title": "Longest Substring Without Repeating Chars",
      "difficulty": "Medium",
      "category": "Sliding Window",
      "num": 3,
      "path": "https://leetcode.com/problems/longest-substring-no-repeat"
    },
    {
      "id": 7,
      "title": "Median Two Sorted Arrays",
      "difficulty": "Hard",
      "category": "Binary Search",
      "num": 4,
      "path": "https://leetcode.com/problems/median-of-two-sorted-arrays"
    },
    {
      "id": 8,
      "title": "Median of Two Sorted Arrays",
      "difficulty": "Hard",
      "category": "Binary Search",
      "num": 4,
      "path": "https://leetcode.com/problems/median-of-two-sorted-arrays"
    },
    {
      "id": 9,
      "title": "Longest Palindromic Substring",
      "difficulty": "Medium",
      "category": "DP",
      "num": 5,
      "path": "https://leetcode.com/problems/longest-palindromic-substring"
    },
    {
      "id": 10,
      "title": "Zigzag Conversion",
      "difficulty": "Medium",
      "category": "String",
      "num": 6,
      "path": "https://leetcode.com/problems/zigzag-conversion"
    },
    {
      "id": 11,
      "title": "Reverse Integer",
      "difficulty": "Medium",
      "category": "Math",
      "num": 7,
      "path": "https://leetcode.com/problems/reverse-integer"
    },
    {
      "id": 12,
      "title": "Palindrome Number",
      "difficulty": "Easy",
      "category": "Math",
      "num": 9,
      "path": "https://leetcode.com/problems/palindrome-number"
    },
    {
      "id": 13,
      "title": "Regular Expression Matching",
      "difficulty": "Hard",
      "category": "DP",
      "num": 10,
      "path": "https://leetcode.com/problems/regular-expression-matching"
    },
    {
      "id": 14,
      "title": "Container With Most Water",
      "difficulty": "Medium",
      "category": "Two Pointers",
      "num": 11,
      "path": "https://leetcode.com/problems/container-with-most-water"
    },
    {
      "id": 15,
      "title": "Longest Common Prefix",
      "difficulty": "Easy",
      "category": "String",
      "num": 14,
      "path": "https://leetcode.com/problems/longest-common-prefix"
    },
    {
      "id": 16,
      "title": "3Sum",
      "difficulty": "Medium",
      "category": "Two Pointers",
      "num": 15,
      "path": "https://leetcode.com/problems/3sum"
    },
    {
      "id": 17,
      "title": "Letter Combinations Phone",
      "difficulty": "Medium",
      "category": "Backtracking",
      "num": 17,
      "path": "https://leetcode.com/problems/letter-combinations-phone-number"
    },
    {
      "id": 18,
      "title": "Letter Combinations of a Phone Number",
      "difficulty": "Medium",
      "category": "Backtracking",
      "num": 17,
      "path": "https://leetcode.com/problems/letter-combinations-phone-number"
    },
    {
      "id": 19,
      "title": "4Sum",
      "difficulty": "Medium",
      "category": "Two Pointers",
      "num": 18,
      "path": "https://leetcode.com/problems/4sum"
    },
    {
      "id": 20,
      "title": "Remove Nth Node From End",
      "difficulty": "Medium",
      "category": "Linked List",
      "num": 19,
      "path": "https://leetcode.com/problems/remove-nth-node-end-list"
    },
    {
      "id": 21,
      "title": "Remove Nth Node From End of List",
      "difficulty": "Medium",
      "category": "Linked List",
      "num": 19,
      "path": "https://leetcode.com/problems/remove-nth-node-end-list"
    },
    {
      "id": 22,
      "title": "Valid Parentheses",
      "difficulty": "Easy",
      "category": "Stack",
      "num": 20,
      "path": "https://leetcode.com/problems/valid-parentheses"
    },
    {
      "id": 23,
      "title": "Merge Two Sorted Lists",
      "difficulty": "Easy",
      "category": "Linked List",
      "num": 21,
      "path": "https://leetcode.com/problems/merge-two-sorted-lists"
    },
    {
      "id": 24,
      "title": "Generate Parentheses",
      "difficulty": "Medium",
      "category": "Backtracking",
      "num": 22,
      "path": "https://leetcode.com/problems/generate-parentheses"
    },
    {
      "id": 25,
      "title": "Merge K Sorted Lists",
      "difficulty": "Hard",
      "category": "Heap",
      "num": 23,
      "path": "https://leetcode.com/problems/merge-k-sorted-lists"
    },
    {
      "id": 26,
      "title": "Swap Nodes in Pairs",
      "difficulty": "Medium",
      "category": "Linked List",
      "num": 24,
      "path": "https://leetcode.com/problems/swap-nodes-in-pairs"
    },
    {
      "id": 27,
      "title": "Reverse Nodes in k-Group",
      "difficulty": "Hard",
      "category": "Linked List",
      "num": 25,
      "path": "https://leetcode.com/problems/reverse-nodes-in-k-group"
    },
    {
      "id": 28,
      "title": "Remove Duplicates from Sorted Array",
      "difficulty": "Easy",
      "category": "Two Pointers",
      "num": 26,
      "path": "https://leetcode.com/problems/remove-duplicates-sorted-array"
    },
    {
      "id": 29,
      "title": "Next Permutation",
      "difficulty": "Medium",
      "category": "Array",
      "num": 31,
      "path": "https://leetcode.com/problems/next-permutation"
    },
    {
      "id": 30,
      "title": "Search Rotated Sorted Array",
      "difficulty": "Medium",
      "category": "Binary Search",
      "num": 33,
      "path": "https://leetcode.com/problems/search-rotated-sorted-array"
    },
    {
      "id": 31,
      "title": "Search in Rotated Sorted Array",
      "difficulty": "Medium",
      "category": "Binary Search",
      "num": 33,
      "path": "https://leetcode.com/problems/search-rotated-sorted-array"
    },
    {
      "id": 32,
      "title": "Find First Last Position",
      "difficulty": "Medium",
      "category": "Binary Search",
      "num": 34,
      "path": "https://leetcode.com/problems/find-first-last-position"
    },
    {
      "id": 33,
      "title": "Find First and Last Position of Element",
      "difficulty": "Medium",
      "category": "Binary Search",
      "num": 34,
      "path": "https://leetcode.com/problems/find-first-last-position"
    },
    {
      "id": 34,
      "title": "Search Insert Position",
      "difficulty": "Easy",
      "category": "Binary Search",
      "num": 35,
      "path": "https://leetcode.com/problems/search-insert-position"
    },
    {
      "id": 35,
      "title": "Valid Sudoku",
      "difficulty": "Medium",
      "category": "Hash Table",
      "num": 36,
      "path": "https://leetcode.com/problems/valid-sudoku"
    },
    {
      "id": 36,
      "title": "Sudoku Solver",
      "difficulty": "Hard",
      "category": "Backtracking",
      "num": 37,
      "path": "https://leetcode.com/problems/sudoku-solver"
    },
    {
      "id": 37,
      "title": "Combination Sum",
      "difficulty": "Medium",
      "category": "Backtracking",
      "num": 39,
      "path": "https://leetcode.com/problems/combination-sum"
    },
    {
      "id": 38,
      "title": "Combination Sum II",
      "difficulty": "Medium",
      "category": "Backtracking",
      "num": 40,
      "path": "https://leetcode.com/problems/combination-sum-ii"
    },
    {
      "id": 39,
      "title": "First Missing Positive",
      "difficulty": "Hard",
      "category": "Array",
      "num": 41,
      "path": "https://leetcode.com/problems/first-missing-positive"
    },
    {
      "id": 40,
      "title": "Trapping Rain Water",
      "difficulty": "Hard",
      "category": "Two Pointers",
      "num": 42,
      "path": "https://leetcode.com/problems/trapping-rain-water"
    },
    {
      "id": 41,
      "title": "Multiply Strings",
      "difficulty": "Medium",
      "category": "Math",
      "num": 43,
      "path": "https://leetcode.com/problems/multiply-strings"
    },
    {
      "id": 42,
      "title": "Jump Game II",
      "difficulty": "Medium",
      "category": "Greedy",
      "num": 45,
      "path": "https://leetcode.com/problems/jump-game-ii"
    },
    {
      "id": 43,
      "title": "Permutations",
      "difficulty": "Medium",
      "category": "Backtracking",
      "num": 46,
      "path": "https://leetcode.com/problems/permutations"
    },
    {
      "id": 44,
      "title": "Permutations II",
      "difficulty": "Medium",
      "category": "Backtracking",
      "num": 47,
      "path": "https://leetcode.com/problems/permutations-ii"
    },
    {
      "id": 45,
      "title": "Rotate Image",
      "difficulty": "Medium",
      "category": "Matrix",
      "num": 48,
      "path": "https://leetcode.com/problems/rotate-image"
    },
    {
      "id": 46,
      "title": "Group Anagrams",
      "difficulty": "Medium",
      "category": "Hash Map",
      "num": 49,
      "path": "https://leetcode.com/problems/group-anagrams"
    },
    {
      "id": 47,
      "title": "Pow(x, n)",
      "difficulty": "Medium",
      "category": "Recursion",
      "num": 50,
      "path": "https://leetcode.com/problems/powx-n"
    },
    {
      "id": 48,
      "title": "N-Queens",
      "difficulty": "Hard",
      "category": "Backtracking",
      "num": 51,
      "path": "https://leetcode.com/problems/n-queens"
    },
    {
      "id": 49,
      "title": "Maximum Subarray (Kadane)",
      "difficulty": "Medium",
      "category": "DP",
      "num": 53,
      "path": "https://leetcode.com/problems/maximum-subarray"
    },
    {
      "id": 50,
      "title": "Maximum Subarray",
      "difficulty": "Medium",
      "category": "DP",
      "num": 53,
      "path": "https://leetcode.com/problems/maximum-subarray"
    },
    {
      "id": 51,
      "title": "Spiral Matrix",
      "difficulty": "Medium",
      "category": "Matrix",
      "num": 54,
      "path": "https://leetcode.com/problems/spiral-matrix"
    },
    {
      "id": 52,
      "title": "Jump Game",
      "difficulty": "Medium",
      "category": "Greedy",
      "num": 55,
      "path": "https://leetcode.com/problems/jump-game"
    },
    {
      "id": 53,
      "title": "Merge Intervals",
      "difficulty": "Medium",
      "category": "Interval",
      "num": 56,
      "path": "https://leetcode.com/problems/merge-intervals"
    },
    {
      "id": 54,
      "title": "Insert Interval",
      "difficulty": "Medium",
      "category": "Interval",
      "num": 57,
      "path": "https://leetcode.com/problems/insert-interval"
    },
    {
      "id": 55,
      "title": "Rotate List",
      "difficulty": "Medium",
      "category": "Linked List",
      "num": 61,
      "path": "https://leetcode.com/problems/rotate-list"
    },
    {
      "id": 56,
      "title": "Unique Paths",
      "difficulty": "Medium",
      "category": "DP",
      "num": 62,
      "path": "https://leetcode.com/problems/unique-paths"
    },
    {
      "id": 57,
      "title": "Unique Paths II",
      "difficulty": "Medium",
      "category": "DP",
      "num": 63,
      "path": "https://leetcode.com/problems/unique-paths-ii"
    },
    {
      "id": 58,
      "title": "Minimum Path Sum",
      "difficulty": "Medium",
      "category": "DP",
      "num": 64,
      "path": "https://leetcode.com/problems/minimum-path-sum"
    },
    {
      "id": 59,
      "title": "Plus One",
      "difficulty": "Easy",
      "category": "Math",
      "num": 66,
      "path": "https://leetcode.com/problems/plus-one"
    },
    {
      "id": 60,
      "title": "Climbing Stairs",
      "difficulty": "Easy",
      "category": "DP",
      "num": 70,
      "path": "https://leetcode.com/problems/climbing-stairs"
    },
    {
      "id": 61,
      "title": "Edit Distance",
      "difficulty": "Medium",
      "category": "DP",
      "num": 72,
      "path": "https://leetcode.com/problems/edit-distance"
    },
    {
      "id": 62,
      "title": "Set Matrix Zeroes",
      "difficulty": "Medium",
      "category": "Matrix",
      "num": 73,
      "path": "https://leetcode.com/problems/set-matrix-zeroes"
    },
    {
      "id": 63,
      "title": "Search 2D Matrix",
      "difficulty": "Medium",
      "category": "Binary Search",
      "num": 74,
      "path": "https://leetcode.com/problems/search-a-2d-matrix"
    },
    {
      "id": 64,
      "title": "Search a 2D Matrix",
      "difficulty": "Medium",
      "category": "Binary Search",
      "num": 74,
      "path": "https://leetcode.com/problems/search-a-2d-matrix"
    },
    {
      "id": 65,
      "title": "Sort Colors Dutch Flag",
      "difficulty": "Medium",
      "category": "Sorting",
      "num": 75,
      "path": "https://leetcode.com/problems/sort-colors"
    },
    {
      "id": 66,
      "title": "Sort Colors",
      "difficulty": "Medium",
      "category": "Sorting",
      "num": 75,
      "path": "https://leetcode.com/problems/sort-colors"
    },
    {
      "id": 67,
      "title": "Minimum Window Substring",
      "difficulty": "Hard",
      "category": "Sliding Window",
      "num": 76,
      "path": "https://leetcode.com/problems/minimum-window-substring"
    },
    {
      "id": 68,
      "title": "Combinations",
      "difficulty": "Medium",
      "category": "Backtracking",
      "num": 77,
      "path": "https://leetcode.com/problems/combinations"
    },
    {
      "id": 69,
      "title": "Subsets",
      "difficulty": "Medium",
      "category": "Backtracking",
      "num": 78,
      "path": "https://leetcode.com/problems/subsets"
    },
    {
      "id": 70,
      "title": "Word Search",
      "difficulty": "Medium",
      "category": "Backtracking",
      "num": 79,
      "path": "https://leetcode.com/problems/word-search"
    },
    {
      "id": 71,
      "title": "Remove Duplicates Sorted List II",
      "difficulty": "Medium",
      "category": "Linked List",
      "num": 82,
      "path": "https://leetcode.com/problems/remove-duplicates-sorted-list-ii"
    },
    {
      "id": 72,
      "title": "Remove Duplicates from Sorted List II",
      "difficulty": "Medium",
      "category": "Linked List",
      "num": 82,
      "path": "https://leetcode.com/problems/remove-duplicates-sorted-list-ii"
    },
    {
      "id": 73,
      "title": "Remove Duplicates Sorted List",
      "difficulty": "Easy",
      "category": "Linked List",
      "num": 83,
      "path": "https://leetcode.com/problems/remove-duplicates-sorted-list"
    },
    {
      "id": 74,
      "title": "Largest Rectangle Histogram",
      "difficulty": "Hard",
      "category": "Stack",
      "num": 84,
      "path": "https://leetcode.com/problems/largest-rectangle-in-histogram"
    },
    {
      "id": 75,
      "title": "Largest Rectangle in Histogram",
      "difficulty": "Hard",
      "category": "Stack",
      "num": 84,
      "path": "https://leetcode.com/problems/largest-rectangle-in-histogram"
    },
    {
      "id": 76,
      "title": "Maximal Rectangle",
      "difficulty": "Hard",
      "category": "Stack",
      "num": 85,
      "path": "https://leetcode.com/problems/maximal-rectangle"
    },
    {
      "id": 77,
      "title": "Partition List",
      "difficulty": "Medium",
      "category": "Linked List",
      "num": 86,
      "path": "https://leetcode.com/problems/partition-list"
    },
    {
      "id": 78,
      "title": "Merge Sorted Array",
      "difficulty": "Easy",
      "category": "Two Pointers",
      "num": 88,
      "path": "https://leetcode.com/problems/merge-sorted-array"
    },
    {
      "id": 79,
      "title": "Subsets II",
      "difficulty": "Medium",
      "category": "Backtracking",
      "num": 90,
      "path": "https://leetcode.com/problems/subsets-ii"
    },
    {
      "id": 80,
      "title": "Decode Ways",
      "difficulty": "Medium",
      "category": "DP",
      "num": 91,
      "path": "https://leetcode.com/problems/decode-ways"
    },
    {
      "id": 81,
      "title": "Reverse Linked List II",
      "difficulty": "Medium",
      "category": "Linked List",
      "num": 92,
      "path": "https://leetcode.com/problems/reverse-linked-list-ii"
    },
    {
      "id": 82,
      "title": "Binary Tree Inorder Traversal",
      "difficulty": "Easy",
      "category": "Tree",
      "num": 94,
      "path": "https://leetcode.com/problems/binary-tree-inorder-traversal"
    },
    {
      "id": 83,
      "title": "Interleaving String",
      "difficulty": "Medium",
      "category": "DP",
      "num": 97,
      "path": "https://leetcode.com/problems/interleaving-string"
    },
    {
      "id": 84,
      "title": "Validate Binary Search Tree",
      "difficulty": "Medium",
      "category": "Tree",
      "num": 98,
      "path": "https://leetcode.com/problems/validate-binary-search-tree"
    },
    {
      "id": 85,
      "title": "Same Tree",
      "difficulty": "Easy",
      "category": "Tree",
      "num": 100,
      "path": "https://leetcode.com/problems/same-tree"
    },
    {
      "id": 86,
      "title": "Symmetric Tree",
      "difficulty": "Easy",
      "category": "Tree",
      "num": 101,
      "path": "https://leetcode.com/problems/symmetric-tree"
    },
    {
      "id": 88,
      "title": "Binary Tree Level Order Traversal",
      "difficulty": "Medium",
      "category": "Tree",
      "num": 102,
      "path": "https://leetcode.com/problems/binary-tree-level-order-traversal"
    },
    {
      "id": 89,
      "title": "Binary Tree Zigzag Level Order",
      "difficulty": "Medium",
      "category": "Tree",
      "num": 103,
      "path": "https://leetcode.com/problems/binary-tree-zigzag-level-order-traversal"
    },
    {
      "id": 90,
      "title": "Maximum Depth Binary Tree",
      "difficulty": "Easy",
      "category": "Tree",
      "num": 104,
      "path": "https://leetcode.com/problems/maximum-depth-binary-tree"
    },
    {
      "id": 91,
      "title": "Maximum Depth of Binary Tree",
      "difficulty": "Easy",
      "category": "Tree",
      "num": 104,
      "path": "https://leetcode.com/problems/maximum-depth-binary-tree"
    },
    {
      "id": 92,
      "title": "Construct BT Preorder Inorder",
      "difficulty": "Medium",
      "category": "Tree",
      "num": 105,
      "path": "https://leetcode.com/problems/construct-binary-tree-preorder-inorder"
    },
    {
      "id": 93,
      "title": "Construct BT from Preorder and Inorder",
      "difficulty": "Medium",
      "category": "Tree",
      "num": 105,
      "path": "https://leetcode.com/problems/construct-binary-tree-preorder-inorder"
    },
    {
      "id": 94,
      "title": "Construct Binary Tree from Preorder/Inorder",
      "difficulty": "Medium",
      "category": "Tree",
      "num": 105,
      "path": "https://leetcode.com/problems/construct-binary-tree-preorder-inorder"
    },
    {
      "id": 95,
      "title": "Construct BT Inorder Postorder",
      "difficulty": "Medium",
      "category": "Tree",
      "num": 106,
      "path": "https://leetcode.com/problems/construct-binary-tree-inorder-postorder"
    },
    {
      "id": 96,
      "title": "Construct BT from Inorder and Postorder",
      "difficulty": "Medium",
      "category": "Tree",
      "num": 106,
      "path": "https://leetcode.com/problems/construct-binary-tree-inorder-postorder"
    },
    {
      "id": 97,
      "title": "Balanced Binary Tree",
      "difficulty": "Easy",
      "category": "Tree",
      "num": 110,
      "path": "https://leetcode.com/problems/balanced-binary-tree"
    },
    {
      "id": 98,
      "title": "Minimum Depth Binary Tree",
      "difficulty": "Easy",
      "category": "Tree",
      "num": 111,
      "path": "https://leetcode.com/problems/minimum-depth-of-binary-tree"
    },
    {
      "id": 99,
      "title": "Path Sum",
      "difficulty": "Easy",
      "category": "Tree",
      "num": 112,
      "path": "https://leetcode.com/problems/path-sum"
    },
    {
      "id": 100,
      "title": "Path Sum II",
      "difficulty": "Medium",
      "category": "Tree",
      "num": 113,
      "path": "https://leetcode.com/problems/path-sum-ii"
    },
    {
      "id": 101,
      "title": "Distinct Subsequences",
      "difficulty": "Hard",
      "category": "DP",
      "num": 115,
      "path": "https://leetcode.com/problems/distinct-subsequences"
    },
    {
      "id": 103,
      "title": "Best Time to Buy and Sell Stock",
      "difficulty": "Easy",
      "category": "Greedy",
      "num": 121,
      "path": "https://leetcode.com/problems/best-time-to-buy-and-sell-stock"
    },
    {
      "id": 105,
      "title": "Best Time to Buy and Sell Stock II",
      "difficulty": "Medium",
      "category": "Greedy",
      "num": 122,
      "path": "https://leetcode.com/problems/best-time-to-buy-and-sell-stock-ii"
    },
    {
      "id": 106,
      "title": "Best Time Buy Sell Stock III",
      "difficulty": "Hard",
      "category": "DP",
      "num": 123,
      "path": "https://leetcode.com/problems/best-time-to-buy-and-sell-stock-iii"
    },
    {
      "id": 107,
      "title": "Binary Tree Maximum Path Sum",
      "difficulty": "Hard",
      "category": "Tree",
      "num": 124,
      "path": "https://leetcode.com/problems/binary-tree-maximum-path-sum"
    },
    {
      "id": 108,
      "title": "Valid Palindrome",
      "difficulty": "Easy",
      "category": "String",
      "num": 125,
      "path": "https://leetcode.com/problems/valid-palindrome"
    },
    {
      "id": 109,
      "title": "Word Ladder II",
      "difficulty": "Hard",
      "category": "Graph",
      "num": 126,
      "path": "https://leetcode.com/problems/word-ladder-ii"
    },
    {
      "id": 110,
      "title": "Word Ladder",
      "difficulty": "Hard",
      "category": "Graph",
      "num": 127,
      "path": "https://leetcode.com/problems/word-ladder"
    },
    {
      "id": 111,
      "title": "Longest Consecutive Sequence",
      "difficulty": "Medium",
      "category": "Hash Map",
      "num": 128,
      "path": "https://leetcode.com/problems/longest-consecutive-sequence"
    },
    {
      "id": 112,
      "title": "Surrounded Regions",
      "difficulty": "Medium",
      "category": "Graph",
      "num": 130,
      "path": "https://leetcode.com/problems/surrounded-regions"
    },
    {
      "id": 113,
      "title": "Palindrome Partitioning",
      "difficulty": "Medium",
      "category": "Backtracking",
      "num": 131,
      "path": "https://leetcode.com/problems/palindrome-partitioning"
    },
    {
      "id": 114,
      "title": "Clone Graph",
      "difficulty": "Medium",
      "category": "Graph",
      "num": 133,
      "path": "https://leetcode.com/problems/clone-graph"
    },
    {
      "id": 115,
      "title": "Gas Station",
      "difficulty": "Medium",
      "category": "Greedy",
      "num": 134,
      "path": "https://leetcode.com/problems/gas-station"
    },
    {
      "id": 116,
      "title": "Single Number",
      "difficulty": "Easy",
      "category": "Bit Manipulation",
      "num": 136,
      "path": "https://leetcode.com/problems/single-number"
    },
    {
      "id": 117,
      "title": "Copy List with Random Pointer",
      "difficulty": "Medium",
      "category": "Linked List",
      "num": 138,
      "path": "https://leetcode.com/problems/copy-list-with-random-pointer"
    },
    {
      "id": 118,
      "title": "Word Break",
      "difficulty": "Medium",
      "category": "DP",
      "num": 139,
      "path": "https://leetcode.com/problems/word-break"
    },
    {
      "id": 119,
      "title": "Word Break II",
      "difficulty": "Hard",
      "category": "DP",
      "num": 140,
      "path": "https://leetcode.com/problems/word-break-ii"
    },
    {
      "id": 120,
      "title": "Linked List Cycle",
      "difficulty": "Easy",
      "category": "Linked List",
      "num": 141,
      "path": "https://leetcode.com/problems/detect-cycle-linked-list"
    },
    {
      "id": 121,
      "title": "Linked List Cycle II",
      "difficulty": "Medium",
      "category": "Linked List",
      "num": 141,
      "path": "https://leetcode.com/problems/linked-list-cycle-ii"
    },
    {
      "id": 122,
      "title": "Reorder List",
      "difficulty": "Medium",
      "category": "Linked List",
      "num": 143,
      "path": "https://leetcode.com/problems/reorder-list"
    },
    {
      "id": 123,
      "title": "Binary Tree Postorder Traversal",
      "difficulty": "Easy",
      "category": "Tree",
      "num": 145,
      "path": "https://leetcode.com/problems/binary-tree-postorder-traversal"
    },
    {
      "id": 124,
      "title": "LRU Cache",
      "difficulty": "Medium",
      "category": "Design",
      "num": 146,
      "path": "https://leetcode.com/problems/lru-cache"
    },
    {
      "id": 125,
      "title": "Sort List",
      "difficulty": "Medium",
      "category": "Sorting",
      "num": 148,
      "path": "https://leetcode.com/problems/sort-list"
    },
    {
      "id": 126,
      "title": "Evaluate Reverse Polish Notation",
      "difficulty": "Medium",
      "category": "Stack",
      "num": 150,
      "path": "https://leetcode.com/problems/evaluate-reverse-polish-notation"
    },
    {
      "id": 127,
      "title": "Reverse Words in String",
      "difficulty": "Medium",
      "category": "String",
      "num": 151,
      "path": "https://leetcode.com/problems/reverse-words-in-a-string"
    },
    {
      "id": 128,
      "title": "Reverse Words in a String",
      "difficulty": "Medium",
      "category": "String",
      "num": 151,
      "path": "https://leetcode.com/problems/reverse-words-in-a-string"
    },
    {
      "id": 129,
      "title": "Maximum Product Subarray",
      "difficulty": "Medium",
      "category": "Array",
      "num": 152,
      "path": "https://leetcode.com/problems/maximum-product-subarray"
    },
    {
      "id": 130,
      "title": "Find Min Rotated Sorted Array",
      "difficulty": "Medium",
      "category": "Binary Search",
      "num": 153,
      "path": "https://leetcode.com/problems/find-min-rotated-sorted-array"
    },
    {
      "id": 131,
      "title": "Find Minimum in Rotated Sorted Array",
      "difficulty": "Medium",
      "category": "Binary Search",
      "num": 153,
      "path": "https://leetcode.com/problems/find-min-rotated-sorted-array"
    },
    {
      "id": 132,
      "title": "Min Stack",
      "difficulty": "Medium",
      "category": "Stack",
      "num": 155,
      "path": "https://leetcode.com/problems/min-stack"
    },
    {
      "id": 133,
      "title": "K Distinct Characters",
      "difficulty": "Medium",
      "category": "Sliding Window",
      "num": 159,
      "path": "https://leetcode.com/problems/longest-substring-k-distinct"
    },
    {
      "id": 134,
      "title": "Intersection Two Linked Lists",
      "difficulty": "Easy",
      "category": "Linked List",
      "num": 160,
      "path": "https://leetcode.com/problems/intersection-of-two-linked-lists"
    },
    {
      "id": 135,
      "title": "Intersection of Two Linked Lists",
      "difficulty": "Easy",
      "category": "Linked List",
      "num": 160,
      "path": "https://leetcode.com/problems/intersection-of-two-linked-lists"
    },
    {
      "id": 136,
      "title": "Find Peak Element",
      "difficulty": "Medium",
      "category": "Binary Search",
      "num": 162,
      "path": "https://leetcode.com/problems/find-peak-element"
    },
    {
      "id": 137,
      "title": "Two Sum II - Sorted",
      "difficulty": "Easy",
      "category": "Two Pointers",
      "num": 167,
      "path": "https://leetcode.com/problems/two-sum-ii"
    },
    {
      "id": 140,
      "title": "Majority Element",
      "difficulty": "Easy",
      "category": "Array",
      "num": 169,
      "path": "https://leetcode.com/problems/majority-element"
    },
    {
      "id": 141,
      "title": "BST Iterator",
      "difficulty": "Medium",
      "category": "Tree",
      "num": 173,
      "path": "https://leetcode.com/problems/binary-search-tree-iterator"
    },
    {
      "id": 142,
      "title": "Dungeon Game",
      "difficulty": "Hard",
      "category": "DP",
      "num": 174,
      "path": "https://leetcode.com/problems/dungeon-game"
    },
    {
      "id": 143,
      "title": "Rotate Array",
      "difficulty": "Medium",
      "category": "Array",
      "num": 189,
      "path": "https://leetcode.com/problems/rotate-array"
    },
    {
      "id": 144,
      "title": "Reverse Bits",
      "difficulty": "Easy",
      "category": "Bit Manipulation",
      "num": 190,
      "path": "https://leetcode.com/problems/reverse-bits"
    },
    {
      "id": 145,
      "title": "Number of 1 Bits",
      "difficulty": "Easy",
      "category": "Bit Manipulation",
      "num": 191,
      "path": "https://leetcode.com/problems/number-of-1-bits"
    },
    {
      "id": 146,
      "title": "House Robber",
      "difficulty": "Medium",
      "category": "DP",
      "num": 198,
      "path": "https://leetcode.com/problems/house-robber"
    },
    {
      "id": 147,
      "title": "Binary Tree Right Side View",
      "difficulty": "Medium",
      "category": "Tree",
      "num": 199,
      "path": "https://leetcode.com/problems/binary-tree-right-side-view"
    },
    {
      "id": 148,
      "title": "Number of Islands",
      "difficulty": "Medium",
      "category": "Graph",
      "num": 200,
      "path": "https://leetcode.com/problems/number-of-islands"
    },
    {
      "id": 149,
      "title": "Bitwise AND of Numbers Range",
      "difficulty": "Medium",
      "category": "Bit Manipulation",
      "num": 201,
      "path": "https://leetcode.com/problems/bitwise-and-of-numbers-range"
    },
    {
      "id": 150,
      "title": "Happy Number",
      "difficulty": "Easy",
      "category": "Math",
      "num": 202,
      "path": "https://leetcode.com/problems/happy-number"
    },
    {
      "id": 151,
      "title": "Isomorphic Strings",
      "difficulty": "Easy",
      "category": "Hash Map",
      "num": 205,
      "path": "https://leetcode.com/problems/isomorphic-strings"
    },
    {
      "id": 152,
      "title": "Reverse Linked List",
      "difficulty": "Easy",
      "category": "Linked List",
      "num": 206,
      "path": "https://leetcode.com/problems/reverse-linked-list"
    },
    {
      "id": 153,
      "title": "Course Schedule",
      "difficulty": "Medium",
      "category": "Graph",
      "num": 207,
      "path": "https://leetcode.com/problems/course-schedule"
    },
    {
      "id": 154,
      "title": "Implement Trie Prefix Tree",
      "difficulty": "Medium",
      "category": "Trie",
      "num": 208,
      "path": "https://leetcode.com/problems/implement-trie"
    },
    {
      "id": 155,
      "title": "Implement Trie (Prefix Tree)",
      "difficulty": "Medium",
      "category": "Trie",
      "num": 208,
      "path": "https://leetcode.com/problems/implement-trie"
    },
    {
      "id": 156,
      "title": "Course Schedule II",
      "difficulty": "Medium",
      "category": "Graph",
      "num": 210,
      "path": "https://leetcode.com/problems/course-schedule-ii"
    },
    {
      "id": 157,
      "title": "Add Search Words",
      "difficulty": "Medium",
      "category": "Trie",
      "num": 211,
      "path": "https://leetcode.com/problems/design-add-search-words"
    },
    {
      "id": 158,
      "title": "Design Add and Search Words",
      "difficulty": "Medium",
      "category": "Trie",
      "num": 211,
      "path": "https://leetcode.com/problems/design-add-search-words"
    },
    {
      "id": 159,
      "title": "Word Search II",
      "difficulty": "Hard",
      "category": "Trie",
      "num": 212,
      "path": "https://leetcode.com/problems/word-search-ii"
    },
    {
      "id": 160,
      "title": "House Robber II",
      "difficulty": "Medium",
      "category": "DP",
      "num": 213,
      "path": "https://leetcode.com/problems/house-robber-ii"
    },
    {
      "id": 161,
      "title": "Kth Largest Element Array",
      "difficulty": "Medium",
      "category": "Heap",
      "num": 215,
      "path": "https://leetcode.com/problems/kth-largest-element-in-array"
    },
    {
      "id": 162,
      "title": "Kth Largest Element in an Array",
      "difficulty": "Medium",
      "category": "Sorting",
      "num": 215,
      "path": "https://leetcode.com/problems/kth-largest-element-in-array"
    },
    {
      "id": 163,
      "title": "Combination Sum III",
      "difficulty": "Medium",
      "category": "Backtracking",
      "num": 216,
      "path": "https://leetcode.com/problems/combination-sum-iii"
    },
    {
      "id": 164,
      "title": "Contains Duplicate",
      "difficulty": "Easy",
      "category": "Array",
      "num": 217,
      "path": "https://leetcode.com/problems/contains-duplicate"
    },
    {
      "id": 165,
      "title": "Contains Duplicate II",
      "difficulty": "Easy",
      "category": "Array",
      "num": 219,
      "path": "https://leetcode.com/problems/contains-duplicate-ii"
    },
    {
      "id": 166,
      "title": "Contains Duplicate III",
      "difficulty": "Medium",
      "category": "Array",
      "num": 220,
      "path": "https://leetcode.com/problems/contains-duplicate-iii"
    },
    {
      "id": 167,
      "title": "Implement Stack using Queues",
      "difficulty": "Easy",
      "category": "Design",
      "num": 225,
      "path": "https://leetcode.com/problems/implement-stack-using-queues"
    },
    {
      "id": 168,
      "title": "Invert Binary Tree",
      "difficulty": "Easy",
      "category": "Tree",
      "num": 226,
      "path": "https://leetcode.com/problems/invert-binary-tree"
    },
    {
      "id": 169,
      "title": "Kth Smallest Element BST",
      "difficulty": "Medium",
      "category": "Tree",
      "num": 230,
      "path": "https://leetcode.com/problems/kth-smallest-element-in-bst"
    },
    {
      "id": 170,
      "title": "Kth Smallest Element in a BST",
      "difficulty": "Medium",
      "category": "Tree",
      "num": 230,
      "path": "https://leetcode.com/problems/kth-smallest-element-in-bst"
    },
    {
      "id": 171,
      "title": "Kth Smallest Element in BST",
      "difficulty": "Medium",
      "category": "Tree",
      "num": 230,
      "path": "https://leetcode.com/problems/kth-smallest-element-in-bst"
    },
    {
      "id": 172,
      "title": "Implement Queue using Stacks",
      "difficulty": "Easy",
      "category": "Design",
      "num": 232,
      "path": "https://leetcode.com/problems/implement-queue-using-stacks"
    },
    {
      "id": 173,
      "title": "Palindrome Linked List",
      "difficulty": "Easy",
      "category": "Linked List",
      "num": 234,
      "path": "https://leetcode.com/problems/palindrome-linked-list"
    },
    {
      "id": 174,
      "title": "LCA of BST",
      "difficulty": "Easy",
      "category": "Tree",
      "num": 235,
      "path": "https://leetcode.com/problems/lca-bst"
    },
    {
      "id": 175,
      "title": "Lowest Common Ancestor of BST",
      "difficulty": "Easy",
      "category": "Tree",
      "num": 235,
      "path": "https://leetcode.com/problems/lca-bst"
    },
    {
      "id": 176,
      "title": "LCA of Binary Tree",
      "difficulty": "Medium",
      "category": "Tree",
      "num": 236,
      "path": "https://leetcode.com/problems/lca-binary-tree"
    },
    {
      "id": 177,
      "title": "Lowest Common Ancestor of BT",
      "difficulty": "Medium",
      "category": "Tree",
      "num": 236,
      "path": "https://leetcode.com/problems/lca-binary-tree"
    },
    {
      "id": 178,
      "title": "Product of Array Except Self",
      "difficulty": "Medium",
      "category": "Array",
      "num": 238,
      "path": "https://leetcode.com/problems/product-of-array-except-self"
    },
    {
      "id": 179,
      "title": "Sliding Window Maximum",
      "difficulty": "Hard",
      "category": "Queue",
      "num": 239,
      "path": "https://leetcode.com/problems/sliding-window-maximum"
    },
    {
      "id": 180,
      "title": "Search 2D Matrix II",
      "difficulty": "Medium",
      "category": "Binary Search",
      "num": 240,
      "path": "https://leetcode.com/problems/search-a-2d-matrix-ii"
    },
    {
      "id": 181,
      "title": "Valid Anagram",
      "difficulty": "Easy",
      "category": "Hash Map",
      "num": 242,
      "path": "https://leetcode.com/problems/valid-anagram"
    },
    {
      "id": 182,
      "title": "Meeting Rooms",
      "difficulty": "Easy",
      "category": "Interval",
      "num": 252,
      "path": "https://leetcode.com/problems/meeting-rooms"
    },
    {
      "id": 183,
      "title": "Meeting Rooms II",
      "difficulty": "Medium",
      "category": "Interval",
      "num": 253,
      "path": "https://leetcode.com/problems/meeting-rooms-ii"
    },
    {
      "id": 184,
      "title": "Binary Tree Paths",
      "difficulty": "Easy",
      "category": "Tree",
      "num": 257,
      "path": "https://leetcode.com/problems/binary-tree-paths"
    },
    {
      "id": 185,
      "title": "Single Number III",
      "difficulty": "Medium",
      "category": "Bit Manipulation",
      "num": 260,
      "path": "https://leetcode.com/problems/single-number-iii"
    },
    {
      "id": 186,
      "title": "Graph Valid Tree",
      "difficulty": "Medium",
      "category": "Graph",
      "num": 261,
      "path": "https://leetcode.com/problems/graph-valid-tree"
    },
    {
      "id": 187,
      "title": "Missing Number",
      "difficulty": "Easy",
      "category": "Bit Manipulation",
      "num": 268,
      "path": "https://leetcode.com/problems/missing-number"
    },
    {
      "id": 188,
      "title": "Alien Dictionary",
      "difficulty": "Hard",
      "category": "Graph",
      "num": 269,
      "path": "https://leetcode.com/problems/alien-dictionary"
    },
    {
      "id": 189,
      "title": "Encode Decode Strings",
      "difficulty": "Medium",
      "category": "Design",
      "num": 271,
      "path": "https://leetcode.com/problems/encode-decode-strings"
    },
    {
      "id": 190,
      "title": "Encode and Decode Strings",
      "difficulty": "Medium",
      "category": "Design",
      "num": 271,
      "path": "https://leetcode.com/problems/encode-decode-strings"
    },
    {
      "id": 191,
      "title": "First Bad Version",
      "difficulty": "Easy",
      "category": "Binary Search",
      "num": 278,
      "path": "https://leetcode.com/problems/first-bad-version"
    },
    {
      "id": 192,
      "title": "Wiggle Sort",
      "difficulty": "Medium",
      "category": "Array",
      "num": 280,
      "path": "https://leetcode.com/problems/wiggle-sort"
    },
    {
      "id": 193,
      "title": "Move Zeroes",
      "difficulty": "Easy",
      "category": "Array",
      "num": 283,
      "path": "https://leetcode.com/problems/move-zeroes"
    },
    {
      "id": 194,
      "title": "Walls and Gates",
      "difficulty": "Medium",
      "category": "Graph",
      "num": 286,
      "path": "https://leetcode.com/problems/walls-and-gates"
    },
    {
      "id": 195,
      "title": "Find Duplicate Number",
      "difficulty": "Medium",
      "category": "Two Pointers",
      "num": 287,
      "path": "https://leetcode.com/problems/find-the-duplicate-number"
    },
    {
      "id": 196,
      "title": "Find the Duplicate Number",
      "difficulty": "Medium",
      "category": "Two Pointers",
      "num": 287,
      "path": "https://leetcode.com/problems/find-the-duplicate-number"
    },
    {
      "id": 197,
      "title": "Game of Life",
      "difficulty": "Medium",
      "category": "Matrix",
      "num": 289,
      "path": "https://leetcode.com/problems/game-of-life"
    },
    {
      "id": 198,
      "title": "Word Pattern",
      "difficulty": "Easy",
      "category": "Hash Map",
      "num": 290,
      "path": "https://leetcode.com/problems/word-pattern"
    },
    {
      "id": 199,
      "title": "Find Median Data Stream",
      "difficulty": "Hard",
      "category": "Heap",
      "num": 295,
      "path": "https://leetcode.com/problems/find-median-from-data-stream"
    },
    {
      "id": 200,
      "title": "Find Median from Data Stream",
      "difficulty": "Hard",
      "category": "Heap",
      "num": 295,
      "path": "https://leetcode.com/problems/find-median-from-data-stream"
    },
    {
      "id": 201,
      "title": "Serialize Deserialize Binary Tree",
      "difficulty": "Hard",
      "category": "Tree",
      "num": 297,
      "path": "https://leetcode.com/problems/serialize-deserialize-binary-tree"
    },
    {
      "id": 202,
      "title": "Serialize and Deserialize Binary Tree",
      "difficulty": "Hard",
      "category": "Tree",
      "num": 297,
      "path": "https://leetcode.com/problems/serialize-deserialize-binary-tree"
    },
    {
      "id": 203,
      "title": "Longest Increasing Subsequence",
      "difficulty": "Medium",
      "category": "DP",
      "num": 300,
      "path": "https://leetcode.com/problems/longest-increasing-subsequence"
    },
    {
      "id": 204,
      "title": "Range Sum Query - Immutable",
      "difficulty": "Easy",
      "category": "Prefix Sum",
      "num": 303,
      "path": "https://leetcode.com/problems/range-sum-query-immutable"
    },
    {
      "id": 205,
      "title": "Best Time to Buy/Sell with Cooldown",
      "difficulty": "Medium",
      "category": "DP",
      "num": 309,
      "path": "https://leetcode.com/problems/best-time-buy-sell-cooldown"
    },
    {
      "id": 206,
      "title": "Burst Balloons",
      "difficulty": "Hard",
      "category": "DP",
      "num": 312,
      "path": "https://leetcode.com/problems/burst-balloons"
    },
    {
      "id": 207,
      "title": "Coin Change",
      "difficulty": "Medium",
      "category": "DP",
      "num": 322,
      "path": "https://leetcode.com/problems/coin-change"
    },
    {
      "id": 208,
      "title": "Number Connected Components",
      "difficulty": "Medium",
      "category": "Graph",
      "num": 323,
      "path": "https://leetcode.com/problems/connected-components-undirected-graph"
    },
    {
      "id": 209,
      "title": "Number of Connected Components",
      "difficulty": "Medium",
      "category": "Graph",
      "num": 323,
      "path": "https://leetcode.com/problems/connected-components-undirected-graph"
    },
    {
      "id": 210,
      "title": "Longest Increasing Path in a Matrix",
      "difficulty": "Hard",
      "category": "DP",
      "num": 329,
      "path": "https://leetcode.com/problems/longest-increasing-path-matrix"
    },
    {
      "id": 211,
      "title": "Reconstruct Itinerary",
      "difficulty": "Hard",
      "category": "Graph",
      "num": 332,
      "path": "https://leetcode.com/problems/reconstruct-itinerary"
    },
    {
      "id": 212,
      "title": "Increasing Triplet Subsequence",
      "difficulty": "Medium",
      "category": "Greedy",
      "num": 334,
      "path": "https://leetcode.com/problems/increasing-triplet-subsequence"
    },
    {
      "id": 213,
      "title": "House Robber III",
      "difficulty": "Medium",
      "category": "DP",
      "num": 337,
      "path": "https://leetcode.com/problems/house-robber-iii"
    },
    {
      "id": 214,
      "title": "Counting Bits",
      "difficulty": "Easy",
      "category": "Bit Manipulation",
      "num": 338,
      "path": "https://leetcode.com/problems/counting-bits"
    },
    {
      "id": 215,
      "title": "Reverse String",
      "difficulty": "Easy",
      "category": "Two Pointers",
      "num": 344,
      "path": "https://leetcode.com/problems/reverse-string"
    },
    {
      "id": 216,
      "title": "Top K Frequent Elements",
      "difficulty": "Medium",
      "category": "Heap",
      "num": 347,
      "path": "https://leetcode.com/problems/top-k-frequent-elements"
    },
    {
      "id": 217,
      "title": "Design Twitter",
      "difficulty": "Medium",
      "category": "Design",
      "num": 355,
      "path": "https://leetcode.com/problems/design-twitter"
    },
    {
      "id": 218,
      "title": "Design Hit Counter",
      "difficulty": "Medium",
      "category": "Design",
      "num": 362,
      "path": "https://leetcode.com/problems/design-hit-counter"
    },
    {
      "id": 219,
      "title": "Sum of Two Integers",
      "difficulty": "Medium",
      "category": "Bit Manipulation",
      "num": 371,
      "path": "https://leetcode.com/problems/sum-of-two-integers"
    },
    {
      "id": 220,
      "title": "Combination Sum IV",
      "difficulty": "Medium",
      "category": "DP",
      "num": 377,
      "path": "https://leetcode.com/problems/combination-sum-iv"
    },
    {
      "id": 221,
      "title": "Insert Delete GetRandom O(1)",
      "difficulty": "Medium",
      "category": "Design",
      "num": 380,
      "path": "https://leetcode.com/problems/insert-delete-getrandom-o1"
    },
    {
      "id": 222,
      "title": "Insert Delete GetRandom Duplicates",
      "difficulty": "Hard",
      "category": "Design",
      "num": 381,
      "path": "https://leetcode.com/problems/insert-delete-getrandom-duplicates"
    },
    {
      "id": 223,
      "title": "Ransom Note",
      "difficulty": "Easy",
      "category": "Hash Map",
      "num": 383,
      "path": "https://leetcode.com/problems/ransom-note"
    },
    {
      "id": 224,
      "title": "Is Subsequence",
      "difficulty": "Easy",
      "category": "Two Pointers",
      "num": 392,
      "path": "https://leetcode.com/problems/is-subsequence"
    },
    {
      "id": 225,
      "title": "Decode String",
      "difficulty": "Medium",
      "category": "Stack",
      "num": 394,
      "path": "https://leetcode.com/problems/decode-string"
    },
    {
      "id": 226,
      "title": "Evaluate Division",
      "difficulty": "Medium",
      "category": "Graph",
      "num": 399,
      "path": "https://leetcode.com/problems/evaluate-division"
    },
    {
      "id": 227,
      "title": "Trapping Rain Water II",
      "difficulty": "Hard",
      "category": "Heap",
      "num": 407,
      "path": "https://leetcode.com/problems/trapping-rain-water-ii"
    },
    {
      "id": 228,
      "title": "Partition Equal Subset Sum",
      "difficulty": "Medium",
      "category": "DP",
      "num": 416,
      "path": "https://leetcode.com/problems/partition-equal-subset-sum"
    },
    {
      "id": 229,
      "title": "Pacific Atlantic Water Flow",
      "difficulty": "Medium",
      "category": "Graph",
      "num": 417,
      "path": "https://leetcode.com/problems/pacific-atlantic-water-flow"
    },
    {
      "id": 230,
      "title": "Longest Repeating Char Replacement",
      "difficulty": "Medium",
      "category": "Sliding Window",
      "num": 424,
      "path": "https://leetcode.com/problems/longest-repeating-character-replacement"
    },
    {
      "id": 231,
      "title": "Longest Repeating Character Replacement",
      "difficulty": "Medium",
      "category": "Sliding Window",
      "num": 424,
      "path": "https://leetcode.com/problems/longest-repeating-character-replacement"
    },
    {
      "id": 232,
      "title": "Flatten a Multilevel Doubly Linked List",
      "difficulty": "Medium",
      "category": "Linked List",
      "num": 430,
      "path": "https://leetcode.com/problems/flatten-multilevel-linked-list"
    },
    {
      "id": 233,
      "title": "Minimum Genetic Mutation",
      "difficulty": "Medium",
      "category": "Graph",
      "num": 433,
      "path": "https://leetcode.com/problems/minimum-genetic-mutation"
    },
    {
      "id": 234,
      "title": "Non-overlapping Intervals",
      "difficulty": "Medium",
      "category": "Interval",
      "num": 435,
      "path": "https://leetcode.com/problems/non-overlapping-intervals"
    },
    {
      "id": 235,
      "title": "Non Overlapping Intervals",
      "difficulty": "Medium",
      "category": "Greedy",
      "num": 435,
      "path": "https://leetcode.com/problems/non-overlapping-intervals"
    },
    {
      "id": 236,
      "title": "Find All Anagrams",
      "difficulty": "Medium",
      "category": "Sliding Window",
      "num": 438,
      "path": "https://leetcode.com/problems/find-all-anagrams-in-string"
    },
    {
      "id": 237,
      "title": "Find All Anagrams in a String",
      "difficulty": "Medium",
      "category": "Sliding Window",
      "num": 438,
      "path": "https://leetcode.com/problems/find-all-anagrams-in-string"
    },
    {
      "id": 238,
      "title": "Add Two Numbers II",
      "difficulty": "Medium",
      "category": "Linked List",
      "num": 445,
      "path": "https://leetcode.com/problems/add-two-numbers-ii"
    },
    {
      "id": 239,
      "title": "Serialize Deserialize BST",
      "difficulty": "Medium",
      "category": "Tree",
      "num": 449,
      "path": "https://leetcode.com/problems/serialize-and-deserialize-bst"
    },
    {
      "id": 240,
      "title": "LFU Cache",
      "difficulty": "Hard",
      "category": "Design",
      "num": 460,
      "path": "https://leetcode.com/problems/lfu-cache"
    },
    {
      "id": 241,
      "title": "Sliding Window Median",
      "difficulty": "Hard",
      "category": "Heap",
      "num": 480,
      "path": "https://leetcode.com/problems/sliding-window-median"
    },
    {
      "id": 242,
      "title": "Target Sum",
      "difficulty": "Medium",
      "category": "DP",
      "num": 494,
      "path": "https://leetcode.com/problems/target-sum"
    },
    {
      "id": 243,
      "title": "Next Greater Element I",
      "difficulty": "Easy",
      "category": "Stack",
      "num": 496,
      "path": "https://leetcode.com/problems/next-greater-element-i"
    },
    {
      "id": 244,
      "title": "IPO",
      "difficulty": "Hard",
      "category": "Heap",
      "num": 502,
      "path": "https://leetcode.com/problems/ipo"
    },
    {
      "id": 245,
      "title": "Next Greater Element II",
      "difficulty": "Medium",
      "category": "Stack",
      "num": 503,
      "path": "https://leetcode.com/problems/next-greater-element-ii"
    },
    {
      "id": 246,
      "title": "Coin Change II",
      "difficulty": "Medium",
      "category": "DP",
      "num": 518,
      "path": "https://leetcode.com/problems/coin-change-ii"
    },
    {
      "id": 247,
      "title": "Continuous Subarray Sum",
      "difficulty": "Medium",
      "category": "Prefix Sum",
      "num": 523,
      "path": "https://leetcode.com/problems/continuous-subarray-sum"
    },
    {
      "id": 248,
      "title": "Contiguous Array",
      "difficulty": "Medium",
      "category": "Prefix Sum",
      "num": 525,
      "path": "https://leetcode.com/problems/contiguous-array"
    },
    {
      "id": 249,
      "title": "Reverse String II",
      "difficulty": "Easy",
      "category": "String",
      "num": 541,
      "path": "https://leetcode.com/problems/reverse-string-ii"
    },
    {
      "id": 250,
      "title": "Diameter of Binary Tree",
      "difficulty": "Easy",
      "category": "Tree",
      "num": 543,
      "path": "https://leetcode.com/problems/diameter-of-binary-tree"
    },
    {
      "id": 251,
      "title": "Subarray Sum Equals K",
      "difficulty": "Medium",
      "category": "Prefix Sum",
      "num": 560,
      "path": "https://leetcode.com/problems/subarray-sum-equals-k"
    },
    {
      "id": 252,
      "title": "Permutation in String",
      "difficulty": "Medium",
      "category": "Sliding Window",
      "num": 567,
      "path": "https://leetcode.com/problems/permutation-in-string"
    },
    {
      "id": 253,
      "title": "Subtree of Another Tree",
      "difficulty": "Easy",
      "category": "Tree",
      "num": 572,
      "path": "https://leetcode.com/problems/subtree-of-another-tree"
    },
    {
      "id": 254,
      "title": "Task Scheduler",
      "difficulty": "Medium",
      "category": "Heap",
      "num": 621,
      "path": "https://leetcode.com/problems/task-scheduler"
    },
    {
      "id": 255,
      "title": "Design Circular Queue",
      "difficulty": "Medium",
      "category": "Design",
      "num": 622,
      "path": "https://leetcode.com/problems/design-circular-queue"
    },
    {
      "id": 256,
      "title": "Smallest Range Covering Elements",
      "difficulty": "Hard",
      "category": "Heap",
      "num": 632,
      "path": "https://leetcode.com/problems/smallest-range-covering-elements"
    },
    {
      "id": 257,
      "title": "Decode Ways II",
      "difficulty": "Hard",
      "category": "DP",
      "num": 639,
      "path": "https://leetcode.com/problems/decode-ways-ii"
    },
    {
      "id": 258,
      "title": "Maximum Average Subarray I",
      "difficulty": "Easy",
      "category": "Sliding Window",
      "num": 643,
      "path": "https://leetcode.com/problems/maximum-average-subarray-i"
    },
    {
      "id": 259,
      "title": "Palindromic Substrings",
      "difficulty": "Medium",
      "category": "DP",
      "num": 647,
      "path": "https://leetcode.com/problems/palindromic-substrings"
    },
    {
      "id": 260,
      "title": "Number of LIS",
      "difficulty": "Medium",
      "category": "DP",
      "num": 673,
      "path": "https://leetcode.com/problems/number-of-longest-increasing-subsequence"
    },
    {
      "id": 261,
      "title": "Valid Parenthesis String",
      "difficulty": "Medium",
      "category": "Greedy",
      "num": 678,
      "path": "https://leetcode.com/problems/valid-parenthesis-string"
    },
    {
      "id": 262,
      "title": "Valid Palindrome II",
      "difficulty": "Easy",
      "category": "Two Pointers",
      "num": 680,
      "path": "https://leetcode.com/problems/valid-palindrome-ii"
    },
    {
      "id": 263,
      "title": "Redundant Connection",
      "difficulty": "Medium",
      "category": "Graph",
      "num": 684,
      "path": "https://leetcode.com/problems/redundant-connection"
    },
    {
      "id": 264,
      "title": "Top K Frequent Words",
      "difficulty": "Medium",
      "category": "Heap",
      "num": 692,
      "path": "https://leetcode.com/problems/top-k-frequent-words"
    },
    {
      "id": 265,
      "title": "Max Area of Island",
      "difficulty": "Medium",
      "category": "Graph",
      "num": 695,
      "path": "https://leetcode.com/problems/max-area-of-island"
    },
    {
      "id": 266,
      "title": "Kth Largest Element Stream",
      "difficulty": "Easy",
      "category": "Heap",
      "num": 703,
      "path": "https://leetcode.com/problems/kth-largest-element-in-stream"
    },
    {
      "id": 267,
      "title": "Kth Largest Element in a Stream",
      "difficulty": "Easy",
      "category": "Heap",
      "num": 703,
      "path": "https://leetcode.com/problems/kth-largest-element-in-stream"
    },
    {
      "id": 268,
      "title": "Binary Search",
      "difficulty": "Easy",
      "category": "Binary Search",
      "num": 704,
      "path": "https://leetcode.com/problems/binary-search"
    },
    {
      "id": 269,
      "title": "Design HashMap",
      "difficulty": "Easy",
      "category": "Design",
      "num": 706,
      "path": "https://leetcode.com/problems/design-hashmap"
    },
    {
      "id": 270,
      "title": "Design Linked List",
      "difficulty": "Medium",
      "category": "Linked List",
      "num": 707,
      "path": "https://leetcode.com/problems/design-linked-list"
    },
    {
      "id": 271,
      "title": "Max Length of Repeated Subarray",
      "difficulty": "Medium",
      "category": "DP",
      "num": 718,
      "path": "https://leetcode.com/problems/lcss"
    },
    {
      "id": 272,
      "title": "Accounts Merge",
      "difficulty": "Medium",
      "category": "Graph",
      "num": 721,
      "path": "https://leetcode.com/problems/accounts-merge"
    },
    {
      "id": 273,
      "title": "Daily Temperatures",
      "difficulty": "Medium",
      "category": "Stack",
      "num": 739,
      "path": "https://leetcode.com/problems/daily-temperatures"
    },
    {
      "id": 274,
      "title": "Network Delay Time",
      "difficulty": "Medium",
      "category": "Graph",
      "num": 743,
      "path": "https://leetcode.com/problems/network-delay-time"
    },
    {
      "id": 275,
      "title": "Min Cost Climbing Stairs",
      "difficulty": "Easy",
      "category": "DP",
      "num": 746,
      "path": "https://leetcode.com/problems/min-cost-climbing-stairs"
    },
    {
      "id": 276,
      "title": "Partition Labels",
      "difficulty": "Medium",
      "category": "Greedy",
      "num": 763,
      "path": "https://leetcode.com/problems/partition-labels"
    },
    {
      "id": 277,
      "title": "Reorganize String",
      "difficulty": "Medium",
      "category": "Heap",
      "num": 767,
      "path": "https://leetcode.com/problems/reorganize-string"
    },
    {
      "id": 278,
      "title": "Swim in Rising Water",
      "difficulty": "Hard",
      "category": "Graph",
      "num": 778,
      "path": "https://leetcode.com/problems/swim-in-rising-water"
    },
    {
      "id": 279,
      "title": "Is Graph Bipartite",
      "difficulty": "Medium",
      "category": "Graph",
      "num": 785,
      "path": "https://leetcode.com/problems/is-graph-bipartite"
    },
    {
      "id": 280,
      "title": "Cheapest Flights Within K Stops",
      "difficulty": "Medium",
      "category": "Graph",
      "num": 787,
      "path": "https://leetcode.com/problems/cheapest-flights-within-k-stops"
    },
    {
      "id": 281,
      "title": "Backspace String Compare",
      "difficulty": "Easy",
      "category": "Two Pointers",
      "num": 844,
      "path": "https://leetcode.com/problems/backspace-string-compare"
    },
    {
      "id": 282,
      "title": "Hand of Straights",
      "difficulty": "Medium",
      "category": "Greedy",
      "num": 846,
      "path": "https://leetcode.com/problems/hand-of-straights"
    },
    {
      "id": 283,
      "title": "Car Fleet",
      "difficulty": "Medium",
      "category": "Stack",
      "num": 853,
      "path": "https://leetcode.com/problems/car-fleet"
    },
    {
      "id": 284,
      "title": "Koko Eating Bananas",
      "difficulty": "Medium",
      "category": "Binary Search",
      "num": 875,
      "path": "https://leetcode.com/problems/koko-eating-bananas"
    },
    {
      "id": 285,
      "title": "Middle of the Linked List",
      "difficulty": "Easy",
      "category": "Linked List",
      "num": 876,
      "path": "https://leetcode.com/problems/middle-of-the-linked-list"
    },
    {
      "id": 286,
      "title": "Online Stock Span",
      "difficulty": "Medium",
      "category": "Stack",
      "num": 901,
      "path": "https://leetcode.com/problems/online-stock-span"
    },
    {
      "id": 287,
      "title": "Maximum Sum Circular Subarray",
      "difficulty": "Medium",
      "category": "DP",
      "num": 918,
      "path": "https://leetcode.com/problems/maximum-sum-circular-subarray"
    },
    {
      "id": 288,
      "title": "Number of Recent Calls",
      "difficulty": "Easy",
      "category": "Queue",
      "num": 933,
      "path": "https://leetcode.com/problems/number-of-recent-calls"
    },
    {
      "id": 289,
      "title": "Binary Tree Cameras",
      "difficulty": "Hard",
      "category": "Tree",
      "num": 968,
      "path": "https://leetcode.com/problems/binary-tree-cameras"
    },
    {
      "id": 290,
      "title": "K Closest Points to Origin",
      "difficulty": "Medium",
      "category": "Heap",
      "num": 973,
      "path": "https://leetcode.com/problems/k-closest-points-to-origin"
    },
    {
      "id": 291,
      "title": "Subarray Sums Divisible by K",
      "difficulty": "Medium",
      "category": "Prefix Sum",
      "num": 974,
      "path": "https://leetcode.com/problems/subarray-sums-divisible-by-k"
    },
    {
      "id": 292,
      "title": "Time Based Key-Value Store",
      "difficulty": "Medium",
      "category": "Design",
      "num": 981,
      "path": "https://leetcode.com/problems/time-based-key-value-store"
    },
    {
      "id": 293,
      "title": "Min Cost For Tickets",
      "difficulty": "Medium",
      "category": "DP",
      "num": 983,
      "path": "https://leetcode.com/problems/minimum-cost-for-tickets"
    },
    {
      "id": 294,
      "title": "Interval List Intersections",
      "difficulty": "Medium",
      "category": "Interval",
      "num": 986,
      "path": "https://leetcode.com/problems/interval-list-intersections"
    },
    {
      "id": 295,
      "title": "Rotting Oranges",
      "difficulty": "Medium",
      "category": "Graph",
      "num": 994,
      "path": "https://leetcode.com/problems/rotting-oranges"
    },
    {
      "id": 296,
      "title": "Find Common Characters",
      "difficulty": "Easy",
      "category": "Hash Map",
      "num": 1002,
      "path": "https://leetcode.com/problems/find-common-characters"
    },
    {
      "id": 297,
      "title": "Construct BST from Preorder",
      "difficulty": "Medium",
      "category": "Tree",
      "num": 1008,
      "path": "https://leetcode.com/problems/construct-binary-search-tree-from-preorder-traversal"
    },
    {
      "id": 298,
      "title": "Capacity to Ship Packages",
      "difficulty": "Medium",
      "category": "Binary Search",
      "num": 1011,
      "path": "https://leetcode.com/problems/capacity-to-ship-packages-within-d-days"
    },
    {
      "id": 299,
      "title": "Possible Bipartition",
      "difficulty": "Medium",
      "category": "Graph",
      "num": 1042,
      "path": "https://leetcode.com/problems/possible-bipartition"
    },
    {
      "id": 300,
      "title": "Last Stone Weight",
      "difficulty": "Easy",
      "category": "Heap",
      "num": 1046,
      "path": "https://leetcode.com/problems/last-stone-weight"
    },
    {
      "id": 301,
      "title": "Distant Barcodes",
      "difficulty": "Medium",
      "category": "Heap",
      "num": 1054,
      "path": "https://leetcode.com/problems/distant-barcodes"
    },
    {
      "id": 302,
      "title": "Longest Common Subsequence",
      "difficulty": "Medium",
      "category": "DP",
      "num": 1143,
      "path": "https://leetcode.com/problems/lcs"
    },
    {
      "id": 303,
      "title": "Find Words That Can Be Formed",
      "difficulty": "Easy",
      "category": "Hash Map",
      "num": 1160,
      "path": "https://leetcode.com/problems/find-words-formed-by-characters"
    },
    {
      "id": 304,
      "title": "Maximum Number of Balloons",
      "difficulty": "Easy",
      "category": "Hash Map",
      "num": 1189,
      "path": "https://leetcode.com/problems/maximum-number-of-balloons"
    },
    {
      "id": 305,
      "title": "Remove Covered Intervals",
      "difficulty": "Medium",
      "category": "Interval",
      "num": 1288,
      "path": "https://leetcode.com/problems/remove-covered-intervals"
    },
    {
      "id": 306,
      "title": "Longest Continuous Subarray",
      "difficulty": "Medium",
      "category": "Sliding Window",
      "num": 1438,
      "path": "https://leetcode.com/problems/longest-continuous-subarray"
    },
    {
      "id": 307,
      "title": "Count Good Nodes in Binary Tree",
      "difficulty": "Medium",
      "category": "Tree",
      "num": 1448,
      "path": "https://leetcode.com/problems/count-good-nodes"
    },
    {
      "id": 308,
      "title": "Number of Good Pairs",
      "difficulty": "Easy",
      "category": "Hash Map",
      "num": 1512,
      "path": "https://leetcode.com/problems/number-of-good-pairs"
    },
    {
      "id": 309,
      "title": "Min Add Parentheses Valid",
      "difficulty": "Medium",
      "category": "Greedy",
      "num": 1541,
      "path": "https://leetcode.com/problems/minimum-add-to-make-parentheses-valid"
    },
    {
      "id": 310,
      "title": "Make The String Great",
      "difficulty": "Easy",
      "category": "Stack",
      "num": 1544,
      "path": "https://leetcode.com/problems/make-the-string-great"
    },
    {
      "id": 311,
      "title": "Min Cost to Connect All Points",
      "difficulty": "Medium",
      "category": "Graph",
      "num": 1584,
      "path": "https://leetcode.com/problems/min-cost-connect-all-points"
    },
    {
      "id": 312,
      "title": "Path With Minimum Effort",
      "difficulty": "Medium",
      "category": "Graph",
      "num": 1631,
      "path": "https://leetcode.com/problems/path-with-minimum-effort"
    },
    {
      "id": 313,
      "title": "Minimum Interval to Include Each Query",
      "difficulty": "Hard",
      "category": "Interval",
      "num": 1851,
      "path": "https://leetcode.com/problems/minimum-interval-include-each-query"
    },
    {
      "id": 314,
      "title": "Merge Triplets to Form Target Triplet",
      "difficulty": "Medium",
      "category": "Greedy",
      "num": 1899,
      "path": "https://leetcode.com/problems/merge-triplets-form-target-triplet"
    },
    {
      "id": 315,
      "title": "Detect Squares",
      "difficulty": "Medium",
      "category": "Math",
      "num": 2013,
      "path": "https://leetcode.com/problems/detect-squares"
    },
    {
      "id": 316,
      "title": "Number of Zero-Filled Subarrays",
      "difficulty": "Medium",
      "category": "Array",
      "num": 2484,
      "path": "https://leetcode.com/problems/number-of-zero-filled-subarrays"
    },
    {
      "id": 317,
      "title": "Guess the Word",
      "difficulty": "Medium",
      "category": "Array",
      "num": 317,
      "path": "https://leetcode.com/problems/guess-the-word"
    },
    {
      "id": 318,
      "title": "Encode and Decode TinyURL",
      "difficulty": "Medium",
      "category": "Design",
      "num": 318,
      "path": "https://leetcode.com/problems/encode-and-decode-tinyurl"
    },
    {
      "id": 319,
      "title": "Split Array into Consecutive Subsequences",
      "difficulty": "Medium",
      "category": "Greedy",
      "num": 319,
      "path": "https://leetcode.com/problems/split-array-into-consecutive-subsequences"
    },
    {
      "id": 320,
      "title": "Number of Matching Subsequences",
      "difficulty": "Medium",
      "category": "Hash Map",
      "num": 320,
      "path": "https://leetcode.com/problems/number-of-matching-subsequences"
    },
    {
      "id": 321,
      "title": "Number of Good Ways to Split a String",
      "difficulty": "Medium",
      "category": "String",
      "num": 321,
      "path": "https://leetcode.com/problems/number-of-good-ways-to-split-a-string"
    },
    {
      "id": 322,
      "title": "Maximum Sum of Distinct Subarrays With Length K",
      "difficulty": "Medium",
      "category": "Sliding Window",
      "num": 322,
      "path": "https://leetcode.com/problems/maximum-sum-of-distinct-subarrays-with-length-k"
    },
    {
      "id": 323,
      "title": "Substring with Concatenation of All Words",
      "difficulty": "Medium",
      "category": "Sliding Window",
      "num": 323,
      "path": "https://leetcode.com/problems/substring-with-concatenation-of-all-words"
    },
    {
      "id": 324,
      "title": "Minimum Size Subarray Sum",
      "difficulty": "Medium",
      "category": "Sliding Window",
      "num": 324,
      "path": "https://leetcode.com/problems/minimum-size-subarray-sum"
    },
    {
      "id": 325,
      "title": "Max Consecutive Ones III",
      "difficulty": "Medium",
      "category": "Sliding Window",
      "num": 325,
      "path": "https://leetcode.com/problems/max-consecutive-ones-iii"
    },
    {
      "id": 326,
      "title": "Best Sightseeing Pair",
      "difficulty": "Medium",
      "category": "DP",
      "num": 326,
      "path": "https://leetcode.com/problems/best-sightseeing-pair"
    },
    {
      "id": 327,
      "title": "Remove All Adjacent Duplicates In String",
      "difficulty": "Medium",
      "category": "Stack",
      "num": 327,
      "path": "https://leetcode.com/problems/remove-all-adjacent-duplicates-in-string"
    },
    {
      "id": 328,
      "title": "Remove Duplicate Letters",
      "difficulty": "Medium",
      "category": "Stack",
      "num": 328,
      "path": "https://leetcode.com/problems/remove-duplicate-letters"
    },
    {
      "id": 329,
      "title": "Removing Stars From a String",
      "difficulty": "Medium",
      "category": "Stack",
      "num": 329,
      "path": "https://leetcode.com/problems/removing-stars-from-a-string"
    },
    {
      "id": 330,
      "title": "Basic Calculator II",
      "difficulty": "Medium",
      "category": "Stack",
      "num": 330,
      "path": "https://leetcode.com/problems/basic-calculator-ii"
    },
    {
      "id": 331,
      "title": "Longest Valid Parentheses",
      "difficulty": "Medium",
      "category": "Stack",
      "num": 331,
      "path": "https://leetcode.com/problems/longest-valid-parentheses"
    },
    {
      "id": 332,
      "title": "132 Pattern",
      "difficulty": "Medium",
      "category": "Stack",
      "num": 332,
      "path": "https://leetcode.com/problems/132-pattern"
    },
    {
      "id": 333,
      "title": "Number of Visible People in a Queue",
      "difficulty": "Medium",
      "category": "Stack",
      "num": 333,
      "path": "https://leetcode.com/problems/number-of-visible-people-in-a-queue"
    },
    {
      "id": 334,
      "title": "Time Needed to Buy Tickets",
      "difficulty": "Medium",
      "category": "Queue",
      "num": 334,
      "path": "https://leetcode.com/problems/time-needed-to-buy-tickets"
    },
    {
      "id": 335,
      "title": "Reveal Cards In Increasing Order",
      "difficulty": "Medium",
      "category": "Queue",
      "num": 335,
      "path": "https://leetcode.com/problems/reveal-cards-in-increasing-order"
    },
    {
      "id": 336,
      "title": "Jump Game VI",
      "difficulty": "Medium",
      "category": "DP",
      "num": 336,
      "path": "https://leetcode.com/problems/jump-game-vi"
    },
    {
      "id": 337,
      "title": "Longest Continuous Subarray With Absolute Diff Less Than or Equal to Limit",
      "difficulty": "Medium",
      "category": "Sliding Window",
      "num": 337,
      "path": "https://leetcode.com/problems/longest-continuous-subarray-with-absolute-diff-less-than-or-equal-to-limit"
    },
    {
      "id": 338,
      "title": "Max Value of Equation",
      "difficulty": "Medium",
      "category": "Heap",
      "num": 338,
      "path": "https://leetcode.com/problems/max-value-of-equation"
    },
    {
      "id": 339,
      "title": "Sort Characters By Frequency",
      "difficulty": "Medium",
      "category": "Sorting",
      "num": 339,
      "path": "https://leetcode.com/problems/sort-characters-by-frequency"
    },
    {
      "id": 340,
      "title": "Maximum Gap",
      "difficulty": "Medium",
      "category": "Sorting",
      "num": 340,
      "path": "https://leetcode.com/problems/maximum-gap"
    },
    {
      "id": 341,
      "title": "Convert Sorted List to Binary Search Tree",
      "difficulty": "Medium",
      "category": "Linked List",
      "num": 341,
      "path": "https://leetcode.com/problems/convert-sorted-list-to-binary-search-tree"
    },
    {
      "id": 342,
      "title": "Construct Quad Tree",
      "difficulty": "Medium",
      "category": "Tree",
      "num": 342,
      "path": "https://leetcode.com/problems/construct-quad-tree"
    },
    {
      "id": 343,
      "title": "Maximum Binary Tree",
      "difficulty": "Medium",
      "category": "Tree",
      "num": 343,
      "path": "https://leetcode.com/problems/maximum-binary-tree"
    },
    {
      "id": 344,
      "title": "Reverse Pairs",
      "difficulty": "Medium",
      "category": "Sorting",
      "num": 344,
      "path": "https://leetcode.com/problems/reverse-pairs"
    },
    {
      "id": 345,
      "title": "Find First and Last Position of Element in Sorted Array",
      "difficulty": "Medium",
      "category": "Binary Search",
      "num": 345,
      "path": "https://leetcode.com/problems/find-first-and-last-position-of-element-in-sorted-array"
    },
    {
      "id": 346,
      "title": "Random Pick with Weight",
      "difficulty": "Medium",
      "category": "Binary Search",
      "num": 346,
      "path": "https://leetcode.com/problems/random-pick-with-weight"
    },
    {
      "id": 347,
      "title": "Find in Mountain Array",
      "difficulty": "Medium",
      "category": "Binary Search",
      "num": 347,
      "path": "https://leetcode.com/problems/find-in-mountain-array"
    },
    {
      "id": 348,
      "title": "Binary Tree Zigzag Level Order Traversal",
      "difficulty": "Medium",
      "category": "Tree",
      "num": 348,
      "path": "https://leetcode.com/problems/binary-tree-zigzag-level-order-traversal"
    },
    {
      "id": 349,
      "title": "Populating Next Right Pointers in Each Node II",
      "difficulty": "Medium",
      "category": "Tree",
      "num": 349,
      "path": "https://leetcode.com/problems/populating-next-right-pointers-in-each-node-ii"
    },
    {
      "id": 350,
      "title": "Maximum Width of Binary Tree",
      "difficulty": "Medium",
      "category": "Tree",
      "num": 350,
      "path": "https://leetcode.com/problems/maximum-width-of-binary-tree"
    },
    {
      "id": 351,
      "title": "Binary Tree Preorder Traversal",
      "difficulty": "Medium",
      "category": "Tree",
      "num": 351,
      "path": "https://leetcode.com/problems/binary-tree-preorder-traversal"
    },
    {
      "id": 352,
      "title": "Convert Sorted Array to Binary Search Tree",
      "difficulty": "Medium",
      "category": "Tree",
      "num": 352,
      "path": "https://leetcode.com/problems/convert-sorted-array-to-binary-search-tree"
    },
    {
      "id": 353,
      "title": "Count Complete Tree Nodes",
      "difficulty": "Medium",
      "category": "Tree",
      "num": 353,
      "path": "https://leetcode.com/problems/count-complete-tree-nodes"
    },
    {
      "id": 354,
      "title": "Path Sum III",
      "difficulty": "Medium",
      "category": "Tree",
      "num": 354,
      "path": "https://leetcode.com/problems/path-sum-iii"
    },
    {
      "id": 355,
      "title": "Maximum Difference Between Node and Ancestor",
      "difficulty": "Medium",
      "category": "Tree",
      "num": 355,
      "path": "https://leetcode.com/problems/maximum-difference-between-node-and-ancestor"
    },
    {
      "id": 356,
      "title": "Construct Binary Tree from Preorder and Inorder Traversal",
      "difficulty": "Medium",
      "category": "Tree",
      "num": 356,
      "path": "https://leetcode.com/problems/construct-binary-tree-from-preorder-and-inorder-traversal"
    },
    {
      "id": 357,
      "title": "Construct Binary Tree from Inorder and Postorder Traversal",
      "difficulty": "Medium",
      "category": "Tree",
      "num": 357,
      "path": "https://leetcode.com/problems/construct-binary-tree-from-inorder-and-postorder-traversal"
    },
    {
      "id": 358,
      "title": "Minimum Distance Between BST Nodes",
      "difficulty": "Medium",
      "category": "Tree",
      "num": 358,
      "path": "https://leetcode.com/problems/minimum-distance-between-bst-nodes"
    },
    {
      "id": 359,
      "title": "Minimum Absolute Difference in BST",
      "difficulty": "Medium",
      "category": "Tree",
      "num": 359,
      "path": "https://leetcode.com/problems/minimum-absolute-difference-in-bst"
    },
    {
      "id": 360,
      "title": "Binary Search Tree Iterator",
      "difficulty": "Medium",
      "category": "Tree",
      "num": 360,
      "path": "https://leetcode.com/problems/binary-search-tree-iterator"
    },
    {
      "id": 361,
      "title": "Delete Nodes And Return Forest",
      "difficulty": "Medium",
      "category": "Tree",
      "num": 361,
      "path": "https://leetcode.com/problems/delete-nodes-and-return-forest"
    },
    {
      "id": 362,
      "title": "Lowest Common Ancestor of a Binary Tree",
      "difficulty": "Medium",
      "category": "Tree",
      "num": 362,
      "path": "https://leetcode.com/problems/lowest-common-ancestor-of-a-binary-tree"
    },
    {
      "id": 363,
      "title": "Find Duplicate Subtrees",
      "difficulty": "Medium",
      "category": "Tree",
      "num": 363,
      "path": "https://leetcode.com/problems/find-duplicate-subtrees"
    },
    {
      "id": 364,
      "title": "Flatten Binary Tree to Linked List",
      "difficulty": "Medium",
      "category": "Linked List",
      "num": 364,
      "path": "https://leetcode.com/problems/flatten-binary-tree-to-linked-list"
    },
    {
      "id": 365,
      "title": "Distribute Coins in Binary Tree",
      "difficulty": "Medium",
      "category": "Tree",
      "num": 365,
      "path": "https://leetcode.com/problems/distribute-coins-in-binary-tree"
    },
    {
      "id": 366,
      "title": "Trim a Binary Search Tree",
      "difficulty": "Medium",
      "category": "Tree",
      "num": 366,
      "path": "https://leetcode.com/problems/trim-a-binary-search-tree"
    },
    {
      "id": 367,
      "title": "My Calendar I",
      "difficulty": "Medium",
      "category": "Binary Search",
      "num": 367,
      "path": "https://leetcode.com/problems/my-calendar-i"
    },
    {
      "id": 368,
      "title": "My Calendar II",
      "difficulty": "Medium",
      "category": "Binary Search",
      "num": 368,
      "path": "https://leetcode.com/problems/my-calendar-ii"
    },
    {
      "id": 369,
      "title": "Stock Price Fluctuation",
      "difficulty": "Medium",
      "category": "Heap",
      "num": 369,
      "path": "https://leetcode.com/problems/stock-price-fluctuation"
    },
    {
      "id": 370,
      "title": "Design Add and Search Words Data Structure",
      "difficulty": "Medium",
      "category": "Trie",
      "num": 370,
      "path": "https://leetcode.com/problems/design-add-and-search-words-data-structure"
    },
    {
      "id": 371,
      "title": "Search Suggestions System",
      "difficulty": "Medium",
      "category": "Binary Search",
      "num": 371,
      "path": "https://leetcode.com/problems/search-suggestions-system"
    },
    {
      "id": 372,
      "title": "Longest Word in Dictionary",
      "difficulty": "Medium",
      "category": "Trie",
      "num": 372,
      "path": "https://leetcode.com/problems/longest-word-in-dictionary"
    },
    {
      "id": 373,
      "title": "Maximum XOR of Two Numbers in an Array",
      "difficulty": "Medium",
      "category": "Trie",
      "num": 373,
      "path": "https://leetcode.com/problems/maximum-xor-of-two-numbers-in-an-array"
    },
    {
      "id": 374,
      "title": "Furthest Building You Can Reach",
      "difficulty": "Medium",
      "category": "Heap",
      "num": 374,
      "path": "https://leetcode.com/problems/furthest-building-you-can-reach"
    },
    {
      "id": 375,
      "title": "Single-Threaded CPU",
      "difficulty": "Medium",
      "category": "Heap",
      "num": 375,
      "path": "https://leetcode.com/problems/single-threaded-cpu"
    },
    {
      "id": 376,
      "title": "Process Tasks Using Servers",
      "difficulty": "Medium",
      "category": "Heap",
      "num": 376,
      "path": "https://leetcode.com/problems/process-tasks-using-servers"
    },
    {
      "id": 377,
      "title": "Minimum Number of Arrows to Burst Balloons",
      "difficulty": "Medium",
      "category": "Greedy",
      "num": 377,
      "path": "https://leetcode.com/problems/minimum-number-of-arrows-to-burst-balloons"
    },
    {
      "id": 378,
      "title": "Maximum Number of Events That Can Be Attended",
      "difficulty": "Medium",
      "category": "Heap",
      "num": 378,
      "path": "https://leetcode.com/problems/maximum-number-of-events-that-can-be-attended"
    },
    {
      "id": 379,
      "title": "Find K Pairs with Smallest Sums",
      "difficulty": "Medium",
      "category": "Heap",
      "num": 379,
      "path": "https://leetcode.com/problems/find-k-pairs-with-smallest-sums"
    },
    {
      "id": 380,
      "title": "Kth Smallest Element in a Sorted Matrix",
      "difficulty": "Medium",
      "category": "Heap",
      "num": 380,
      "path": "https://leetcode.com/problems/kth-smallest-element-in-a-sorted-matrix"
    },
    {
      "id": 381,
      "title": "Smallest Range Covering Elements from K Lists",
      "difficulty": "Medium",
      "category": "Heap",
      "num": 381,
      "path": "https://leetcode.com/problems/smallest-range-covering-elements-from-k-lists"
    },
    {
      "id": 382,
      "title": "Design Browser History",
      "difficulty": "Medium",
      "category": "Design",
      "num": 382,
      "path": "https://leetcode.com/problems/design-browser-history"
    },
    {
      "id": 383,
      "title": "Snapshot Array",
      "difficulty": "Medium",
      "category": "Design",
      "num": 383,
      "path": "https://leetcode.com/problems/snapshot-array"
    },
    {
      "id": 384,
      "title": "Design a Food Rating System",
      "difficulty": "Medium",
      "category": "Heap",
      "num": 384,
      "path": "https://leetcode.com/problems/design-a-food-rating-system"
    },
    {
      "id": 385,
      "title": "Maximum Frequency Stack",
      "difficulty": "Medium",
      "category": "Stack",
      "num": 385,
      "path": "https://leetcode.com/problems/maximum-frequency-stack"
    },
    {
      "id": 386,
      "title": "Minimum Add to Make Parentheses Valid",
      "difficulty": "Medium",
      "category": "Greedy",
      "num": 386,
      "path": "https://leetcode.com/problems/minimum-add-to-make-parentheses-valid"
    },
    {
      "id": 387,
      "title": "Minimum Cost to Hire K Workers",
      "difficulty": "Medium",
      "category": "Heap",
      "num": 387,
      "path": "https://leetcode.com/problems/minimum-cost-to-hire-k-workers"
    },
    {
      "id": 388,
      "title": "Candy",
      "difficulty": "Medium",
      "category": "Greedy",
      "num": 388,
      "path": "https://leetcode.com/problems/candy"
    },
    {
      "id": 389,
      "title": "Minimum Number of Refueling Stops",
      "difficulty": "Medium",
      "category": "Heap",
      "num": 389,
      "path": "https://leetcode.com/problems/minimum-number-of-refueling-stops"
    },
    {
      "id": 390,
      "title": "Time Needed to Inform All Employees",
      "difficulty": "Medium",
      "category": "Tree",
      "num": 390,
      "path": "https://leetcode.com/problems/time-needed-to-inform-all-employees"
    },
    {
      "id": 391,
      "title": "All Paths From Source to Target",
      "difficulty": "Medium",
      "category": "Graph",
      "num": 391,
      "path": "https://leetcode.com/problems/all-paths-from-source-to-target"
    },
    {
      "id": 392,
      "title": "Is Graph Bipartite?",
      "difficulty": "Medium",
      "category": "Graph",
      "num": 392,
      "path": "https://leetcode.com/problems/is-graph-bipartite?"
    },
    {
      "id": 393,
      "title": "All Nodes Distance K in Binary Tree",
      "difficulty": "Medium",
      "category": "Tree",
      "num": 393,
      "path": "https://leetcode.com/problems/all-nodes-distance-k-in-binary-tree"
    },
    {
      "id": 394,
      "title": "Employee Importance",
      "difficulty": "Medium",
      "category": "Graph",
      "num": 394,
      "path": "https://leetcode.com/problems/employee-importance"
    },
    {
      "id": 395,
      "title": "Making A Large Island",
      "difficulty": "Medium",
      "category": "Graph",
      "num": 395,
      "path": "https://leetcode.com/problems/making-a-large-island"
    },
    {
      "id": 396,
      "title": "01 Matrix",
      "difficulty": "Medium",
      "category": "Graph",
      "num": 396,
      "path": "https://leetcode.com/problems/01-matrix"
    },
    {
      "id": 397,
      "title": "Open the Lock",
      "difficulty": "Medium",
      "category": "Graph",
      "num": 397,
      "path": "https://leetcode.com/problems/open-the-lock"
    },
    {
      "id": 398,
      "title": "Shortest Path in a Grid with Obstacles Elimination",
      "difficulty": "Medium",
      "category": "Graph",
      "num": 398,
      "path": "https://leetcode.com/problems/shortest-path-in-a-grid-with-obstacles-elimination"
    },
    {
      "id": 399,
      "title": "Bus Routes",
      "difficulty": "Medium",
      "category": "Graph",
      "num": 399,
      "path": "https://leetcode.com/problems/bus-routes"
    },
    {
      "id": 400,
      "title": "Find Eventual Safe States",
      "difficulty": "Medium",
      "category": "Graph",
      "num": 400,
      "path": "https://leetcode.com/problems/find-eventual-safe-states"
    },
    {
      "id": 401,
      "title": "Minimum Height Trees",
      "difficulty": "Medium",
      "category": "Tree",
      "num": 401,
      "path": "https://leetcode.com/problems/minimum-height-trees"
    },
    {
      "id": 402,
      "title": "Sort Items by Groups Respecting Dependencies",
      "difficulty": "Medium",
      "category": "Graph",
      "num": 402,
      "path": "https://leetcode.com/problems/sort-items-by-groups-respecting-dependencies"
    },
    {
      "id": 403,
      "title": "Number of Provinces",
      "difficulty": "Medium",
      "category": "Graph",
      "num": 403,
      "path": "https://leetcode.com/problems/number-of-provinces"
    },
    {
      "id": 404,
      "title": "Minimize Malware Spread",
      "difficulty": "Medium",
      "category": "Graph",
      "num": 404,
      "path": "https://leetcode.com/problems/minimize-malware-spread"
    },
    {
      "id": 405,
      "title": "Path with Maximum Probability",
      "difficulty": "Medium",
      "category": "Graph",
      "num": 405,
      "path": "https://leetcode.com/problems/path-with-maximum-probability"
    },
    {
      "id": 406,
      "title": "Cracking the Safe",
      "difficulty": "Medium",
      "category": "Graph",
      "num": 406,
      "path": "https://leetcode.com/problems/cracking-the-safe"
    },
    {
      "id": 407,
      "title": "Last Stone Weight II",
      "difficulty": "Medium",
      "category": "DP",
      "num": 407,
      "path": "https://leetcode.com/problems/last-stone-weight-ii"
    },
    {
      "id": 408,
      "title": "Perfect Squares",
      "difficulty": "Medium",
      "category": "DP",
      "num": 408,
      "path": "https://leetcode.com/problems/perfect-squares"
    },
    {
      "id": 409,
      "title": "Number of Longest Increasing Subsequence",
      "difficulty": "Medium",
      "category": "DP",
      "num": 409,
      "path": "https://leetcode.com/problems/number-of-longest-increasing-subsequence"
    },
    {
      "id": 410,
      "title": "Russian Doll Envelopes",
      "difficulty": "Medium",
      "category": "DP",
      "num": 410,
      "path": "https://leetcode.com/problems/russian-doll-envelopes"
    },
    {
      "id": 411,
      "title": "Triangle",
      "difficulty": "Medium",
      "category": "DP",
      "num": 411,
      "path": "https://leetcode.com/problems/triangle"
    },
    {
      "id": 412,
      "title": "Count Square Submatrices with All Ones",
      "difficulty": "Medium",
      "category": "DP",
      "num": 412,
      "path": "https://leetcode.com/problems/count-square-submatrices-with-all-ones"
    },
    {
      "id": 413,
      "title": "Maximum Number of Points with Cost",
      "difficulty": "Medium",
      "category": "DP",
      "num": 413,
      "path": "https://leetcode.com/problems/maximum-number-of-points-with-cost"
    },
    {
      "id": 414,
      "title": "Maximum Profit in Job Scheduling",
      "difficulty": "Medium",
      "category": "DP",
      "num": 414,
      "path": "https://leetcode.com/problems/maximum-profit-in-job-scheduling"
    },
    {
      "id": 415,
      "title": "Cherry Pickup",
      "difficulty": "Medium",
      "category": "DP",
      "num": 415,
      "path": "https://leetcode.com/problems/cherry-pickup"
    },
    {
      "id": 416,
      "title": "Longest Palindromic Subsequence",
      "difficulty": "Medium",
      "category": "DP",
      "num": 416,
      "path": "https://leetcode.com/problems/longest-palindromic-subsequence"
    },
    {
      "id": 417,
      "title": "Wildcard Matching",
      "difficulty": "Medium",
      "category": "DP",
      "num": 417,
      "path": "https://leetcode.com/problems/wildcard-matching"
    },
    {
      "id": 418,
      "title": "Palindrome Partitioning II",
      "difficulty": "Medium",
      "category": "DP",
      "num": 418,
      "path": "https://leetcode.com/problems/palindrome-partitioning-ii"
    },
    {
      "id": 419,
      "title": "Unique Binary Search Trees II",
      "difficulty": "Medium",
      "category": "Tree",
      "num": 419,
      "path": "https://leetcode.com/problems/unique-binary-search-trees-ii"
    },
    {
      "id": 420,
      "title": "Number of Ways to Arrive at Destination",
      "difficulty": "Medium",
      "category": "Graph",
      "num": 420,
      "path": "https://leetcode.com/problems/number-of-ways-to-arrive-at-destination"
    },
    {
      "id": 421,
      "title": "Sum of Distances in Tree",
      "difficulty": "Medium",
      "category": "Tree",
      "num": 421,
      "path": "https://leetcode.com/problems/sum-of-distances-in-tree"
    },
    {
      "id": 422,
      "title": "Minimum Number of Work Sessions to Finish the Tasks",
      "difficulty": "Medium",
      "category": "Backtracking",
      "num": 422,
      "path": "https://leetcode.com/problems/minimum-number-of-work-sessions-to-finish-the-tasks"
    },
    {
      "id": 423,
      "title": "Fair Distribution of Cookies",
      "difficulty": "Medium",
      "category": "Backtracking",
      "num": 423,
      "path": "https://leetcode.com/problems/fair-distribution-of-cookies"
    },
    {
      "id": 424,
      "title": "Shortest Path Visiting All Nodes",
      "difficulty": "Medium",
      "category": "Graph",
      "num": 424,
      "path": "https://leetcode.com/problems/shortest-path-visiting-all-nodes"
    },
    {
      "id": 425,
      "title": "Count Numbers with Unique Digits",
      "difficulty": "Medium",
      "category": "Math",
      "num": 425,
      "path": "https://leetcode.com/problems/count-numbers-with-unique-digits"
    },
    {
      "id": 426,
      "title": "Number of Digit One",
      "difficulty": "Medium",
      "category": "Math",
      "num": 426,
      "path": "https://leetcode.com/problems/number-of-digit-one"
    },
    {
      "id": 427,
      "title": "Numbers At Most N Given Digit Set",
      "difficulty": "Medium",
      "category": "Math",
      "num": 427,
      "path": "https://leetcode.com/problems/numbers-at-most-n-given-digit-set"
    },
    {
      "id": 428,
      "title": "Knight Probability in Chessboard",
      "difficulty": "Medium",
      "category": "DP",
      "num": 428,
      "path": "https://leetcode.com/problems/knight-probability-in-chessboard"
    },
    {
      "id": 429,
      "title": "Soup Servings",
      "difficulty": "Medium",
      "category": "DP",
      "num": 429,
      "path": "https://leetcode.com/problems/soup-servings"
    },
    {
      "id": 430,
      "title": "New 21 Game",
      "difficulty": "Medium",
      "category": "DP",
      "num": 430,
      "path": "https://leetcode.com/problems/new-21-game"
    },
    {
      "id": 431,
      "title": "Best Time to Buy and Sell Stock with Cooldown",
      "difficulty": "Medium",
      "category": "DP",
      "num": 431,
      "path": "https://leetcode.com/problems/best-time-to-buy-and-sell-stock-with-cooldown"
    },
    {
      "id": 432,
      "title": "Best Time to Buy and Sell Stock III",
      "difficulty": "Medium",
      "category": "DP",
      "num": 432,
      "path": "https://leetcode.com/problems/best-time-to-buy-and-sell-stock-iii"
    },
    {
      "id": 433,
      "title": "Factorial Trailing Zeroes",
      "difficulty": "Medium",
      "category": "Math",
      "num": 433,
      "path": "https://leetcode.com/problems/factorial-trailing-zeroes"
    },
    {
      "id": 434,
      "title": "Valid Square",
      "difficulty": "Medium",
      "category": "Math",
      "num": 434,
      "path": "https://leetcode.com/problems/valid-square"
    },
    {
      "id": 435,
      "title": "Minimum Area Rectangle II",
      "difficulty": "Medium",
      "category": "Math",
      "num": 435,
      "path": "https://leetcode.com/problems/minimum-area-rectangle-ii"
    },
    {
      "id": 436,
      "title": "Max Points on a Line",
      "difficulty": "Medium",
      "category": "Math",
      "num": 436,
      "path": "https://leetcode.com/problems/max-points-on-a-line"
    },
    {
      "id": 437,
      "title": "Repeated String Match",
      "difficulty": "Medium",
      "category": "String",
      "num": 437,
      "path": "https://leetcode.com/problems/repeated-string-match"
    },
    {
      "id": 438,
      "title": "Shortest Palindrome",
      "difficulty": "Medium",
      "category": "String",
      "num": 438,
      "path": "https://leetcode.com/problems/shortest-palindrome"
    },
    {
      "id": 439,
      "title": "Longest Duplicate Substring",
      "difficulty": "Medium",
      "category": "Binary Search",
      "num": 439,
      "path": "https://leetcode.com/problems/longest-duplicate-substring"
    },
    {
      "id": 440,
      "title": "Range Sum Query - Mutable",
      "difficulty": "Medium",
      "category": "Segment Tree",
      "num": 440,
      "path": "https://leetcode.com/problems/range-sum-query---mutable"
    },
    {
      "id": 441,
      "title": "Count of Smaller Numbers After Self",
      "difficulty": "Medium",
      "category": "Sorting",
      "num": 441,
      "path": "https://leetcode.com/problems/count-of-smaller-numbers-after-self"
    },
    {
      "id": 442,
      "title": "The Skyline Problem",
      "difficulty": "Medium",
      "category": "Heap",
      "num": 442,
      "path": "https://leetcode.com/problems/the-skyline-problem"
    }
  ]
}